mastodon_social_graph/__init__.py
mastodon_social_graph/database.py
mastodon_social_graph/graph.py
mastodon_social_graph-0.2301.0.dist-info/LICENSE
mastodon_social_graph-0.2301.0.dist-info/METADATA
mastodon_social_graph-0.2301.0.dist-info/WHEEL
mastodon_social_graph-0.2301.0.dist-info/top_level.txt
mastodon_social_graph-0.2301.0.dist-info/RECORD
